pyttings/__init__.py
pyttings/core.py
pyttings/exceptions.py
pyttings/type_converter.py
pyttings-2.1.0.dist-info/LICENSE
pyttings-2.1.0.dist-info/METADATA
pyttings-2.1.0.dist-info/WHEEL
pyttings-2.1.0.dist-info/top_level.txt
pyttings-2.1.0.dist-info/RECORD
