Metadata-Version: 2.2
Name: pyttings
Version: 2.1.0
Summary: Python settings management with namespacing and modular files. Inspired by Django.
Author: Rui Catarino
License: MIT License
Project-URL: Homepage, https://github.com/ruitcatarino/pyttings
Project-URL: Repository, https://github.com/ruitcatarino/pyttings
Project-URL: Issues, https://github.com/ruitcatarino/pyttings/issues
Classifier: Development Status :: 5 - Production/Stable
Classifier: Programming Language :: Python :: 3
Classifier: Intended Audience :: Developers
Classifier: License :: OSI Approved :: MIT License
Classifier: Operating System :: OS Independent
Requires-Python: >=3.10
License-File: LICENSE
